odoo/addons/stock_analysis/README.rst
odoo/addons/stock_analysis/__init__.py
odoo/addons/stock_analysis/__manifest__.py
odoo/addons/stock_analysis/i18n/es.po
odoo/addons/stock_analysis/i18n/fr.po
odoo/addons/stock_analysis/i18n/it.po
odoo/addons/stock_analysis/i18n/pt.po
odoo/addons/stock_analysis/i18n/sl.po
odoo/addons/stock_analysis/i18n/stock_analysis.pot
odoo/addons/stock_analysis/readme/CONTRIBUTORS.rst
odoo/addons/stock_analysis/readme/DESCRIPTION.rst
odoo/addons/stock_analysis/report/__init__.py
odoo/addons/stock_analysis/report/stock_analysis.py
odoo/addons/stock_analysis/report/stock_analysis_view.xml
odoo/addons/stock_analysis/security/ir.model.access.csv
odoo/addons/stock_analysis/static/description/demo_analysis.png
odoo/addons/stock_analysis/static/description/icon.png
odoo/addons/stock_analysis/static/description/index.html
odoo12_addon_stock_analysis-12.0.1.0.0.99.dev17.dist-info/METADATA
odoo12_addon_stock_analysis-12.0.1.0.0.99.dev17.dist-info/WHEEL
odoo12_addon_stock_analysis-12.0.1.0.0.99.dev17.dist-info/top_level.txt
odoo12_addon_stock_analysis-12.0.1.0.0.99.dev17.dist-info/RECORD
